longitudinal_trend/__init__.py
longitudinal_trend-0.0.2.dist-info/LICENSE
longitudinal_trend-0.0.2.dist-info/METADATA
longitudinal_trend-0.0.2.dist-info/WHEEL
longitudinal_trend-0.0.2.dist-info/top_level.txt
longitudinal_trend-0.0.2.dist-info/RECORD
