Metadata-Version: 2.1
Name: longitudinal-trend
Version: 0.0.2
Summary: Download long-term longitudinal Google Trends
Author-email: Mohammad Saleh Ahsan Sakir <ahsansakir506@gmail.com>
License: MIT
Project-URL: homepage, https://github.com/Mohammad-sakir/longitudinalTrends
Keywords: google trends api search longtrends cross section
Classifier: Programming Language :: Python :: 3
Classifier: Development Status :: 1 - Planning
Classifier: Intended Audience :: Developers
Classifier: License :: OSI Approved :: MIT License
Classifier: Operating System :: OS Independent
Requires-Python: >=3.6
License-File: LICENSE
Requires-Dist: ipython
Requires-Dist: pandas
Requires-Dist: python-dateutil
Requires-Dist: pytrends
Requires-Dist: rich
